gtic/TIC.py
gtic/__init__.py
gtic/mlp.py
gtic-1.0.1.dist-info/DESCRIPTION.rst
gtic-1.0.1.dist-info/METADATA
gtic-1.0.1.dist-info/RECORD
gtic-1.0.1.dist-info/WHEEL
gtic-1.0.1.dist-info/metadata.json
gtic-1.0.1.dist-info/top_level.txt
